Assignment2/cordic.v
module cordiciter(input clk,input signed  [15:0] Xin,input signed  [15:0] Yin,input   [15:0] Zin,input signed[15:0] prev_angle,output reg [15:0] Xout,output reg [15:0] Yout,output reg [15:0] Zout,input [2:0] i);
always @(posedge clk)
begin
    Xout<=Zin[15]? Xin+(Yin>>>i) : Xin-(Yin>>>i);
    Yout<=Zin[15]? Yin-(Xin>>>i) : Yin+(Xin>>>i);
    Zout<=Zin[15]? Zin+prev_angle : Zin-prev_angle;
end
endmodule

module Cordic(input clk,input signed  [15:0] Xin, input signed  [15:0] Yin, input  [15:0]  angle, output reg signed  [15:0]Xout, output reg signed  [15:0]Yout);

   real allcosmulfactor=0.612;
   wire[15:0] Xi[0:7]; //for each stage the output of x 
   reg[15:0] x;
   assign Xi[0]=x;

   wire[15:0] Yi[0:7]; //for each stage output of y
   reg[15:0] y;
   assign Yi[0]=y;
   
 
   wire[15:0] Z[0:7]; //after each stage rotated angle 
   reg[15:0] z;
   assign Z[0]=z;   

   wire signed [15:0]Xf;
   wire signed [15:0]Yf;
   wire [15:0] angle_rotated_total;
	
   wire [15:0] angles [0:7];
	assign angles[0] = 16'b0010000000000000; 
   assign angles[1] = 16'b0001001011100100; 
   assign angles[2] = 16'b0000100111111011; 
   assign angles[3] = 16'b0000010100010001; 
   assign angles[4] = 16'b0000001010001011;
   assign angles[5] = 16'b0000000101000101;
   assign angles[6] = 16'b0000000010100010;
   assign angles[7] = 16'b0000000001010001;



   cordiciter c0(clk,Xi[0],Yi[0],Z[0],angles[0],Xi[1],Yi[1],Z[1],3'd0);
   cordiciter c1(clk,Xi[1],Yi[1],Z[1],angles[1],Xi[2],Yi[2],Z[2],3'd1);
   cordiciter c2(clk,Xi[2],Yi[2],Z[2],angles[2],Xi[3],Yi[3],Z[3],3'd2);
   cordiciter c3(clk,Xi[3],Yi[3],Z[3],angles[3],Xi[4],Yi[4],Z[4],3'd3);
   cordiciter c4(clk,Xi[4],Yi[4],Z[4],angles[4],Xi[5],Yi[5],Z[5],3'd4);
   cordiciter c5(clk,Xi[5],Yi[5],Z[5],angles[5],Xi[6],Yi[6],Z[6],3'd5);
   cordiciter c6(clk,Xi[6],Yi[6],Z[6],angles[6],Xi[7],Yi[7],Z[7],3'd6);
   cordiciter c7(clk,Xi[7],Yi[7],Z[7],angles[7],Xf,Yf,angle_rotated_total,3'd7);
   // we are designing 

   always @(posedge clk)
   begin
      case (angle[15:14])
      2'b00: // 0 to 89 
         begin
            x=Xin;
            y=Yin;
            z=angle;
         end
      2'b01: // 90 to 179
         begin
            x=-Yin;
            y=Xin;
            z={2'b00,angle[13:0]};
         end
      2'b10: //180 to 269
         begin
            x=-Xin;
            y=-Yin;
            z={2'b00,angle[13:0]};
         end
      2'b11: //270 to 359
         begin
            x=Yin;
            y=-Xin;
            z={2'b00,angle[13:0]};
         end
   endcase

   // >>> means shifting but with not changing the sign (signed shift operator)
   // the factor we multiplied because atlast we have all cos factor 
   Xout=Xf*allcosmulfactor;
   Yout=Yf*allcosmulfactor;
   end
endmodule

Assignment2/testbench.v
`timescale 1ns/1ns

module cordic_tb;
reg clk=1;   
reg [15:0] angle;
reg  signed  [15:0] Xin;
reg  signed  [15:0] Yin;
real t; //for displaying angle
wire signed  [15:0] Xout;
wire signed  [15:0] Yout;

integer scaleingfactor=2**(16);

// I took angle as angle*(2^16)/360 so that all angles from 0 to 360 can be denoted by 16 bit unsigned binary numbers because as angle<=350 so max value that should represented is 2^16-1 when angle is 359deg which can be represented by a all 1s in 16bit binary 

always #1 clk=~clk;

Cordic cordic(clk, Xin, Yin,angle, Xout, Yout);

initial 
begin
   Xin=16'd1000;
   Yin=16'd1000;
   angle=16'b1110000000000000;
   t=(angle*360.00)/scaleingfactor;
   $monitor("time=%d Xin=%d Yin=%d angle=%fdeg Xout=%d,Yout=%d",$time,Xin,Yin,t,Xout,Yout);
   $dumpfile("cordic.vcd");
   $dumpvars();
   #114 $finish;
end

initial 
begin
   // manual testcases it takes 8 clock cycles to compute single thing so will give input after 8 clock cycles i.e 16ns
   #16 Xin=16'd1000;Yin=16'd1000;angle=16'b1000000000000000;t=(angle*360.00)/scaleingfactor;
   #16 Xin=16'd0;Yin=16'd1000;angle=16'b0000000100000000;t=(angle*360.00)/scaleingfactor;
   #16 Xin=16'd1000;Yin=16'd0;angle=16'b0010000000001000;t=(angle*360.00)/scaleingfactor;
   #16 Xin=16'd1000;Yin=16'd0;angle=16'b0100000000000000;t=(angle*360.00)/scaleingfactor;
   #16 Xin=16'd1000;Yin=16'd0;angle=16'b0000001000100010;t=(angle*360.00)/scaleingfactor;
   #16 Xin=16'd1000;Yin=16'd0;angle=16'b0001001000100010;t=(angle*360.00)/scaleingfactor;
end
endmodule

Assignment2/cordic.vcd
$date
	Wed Dec  7 03:43:14 2022
$end
$version
	Icarus Verilog
$end
$timescale
	1ns
$end
$scope module cordic_tb $end
$var wire 16 ! Yout [15:0] $end
$var wire 16 " Xout [15:0] $end
$var reg 16 # Xin [15:0] $end
$var reg 16 $ Yin [15:0] $end
$var reg 16 % angle [15:0] $end
$var reg 1 & clk $end
$var integer 32 ' scaleingfactor [31:0] $end
$var real 1 ( t $end
$scope module cordic $end
$var wire 16 ) Xin [15:0] $end
$var wire 16 * Yin [15:0] $end
$var wire 16 + angle [15:0] $end
$var wire 1 & clk $end
$var wire 16 , angle_rotated_total [15:0] $end
$var wire 16 - Yf [15:0] $end
$var wire 16 . Xf [15:0] $end
$var reg 16 / Xout [15:0] $end
$var reg 16 0 Yout [15:0] $end
$var reg 16 1 x [15:0] $end
$var reg 16 2 y [15:0] $end
$var reg 16 3 z [15:0] $end
$var real 1 4 allcosmulfactor $end
$scope module c0 $end
$var wire 16 5 Xin [15:0] $end
$var wire 16 6 Yin [15:0] $end
$var wire 16 7 Zin [15:0] $end
$var wire 1 & clk $end
$var wire 3 8 i [2:0] $end
$var wire 16 9 prev_angle [15:0] $end
$var reg 16 : Xout [15:0] $end
$var reg 16 ; Yout [15:0] $end
$var reg 16 < Zout [15:0] $end
$upscope $end
$scope module c1 $end
$var wire 16 = Xin [15:0] $end
$var wire 16 > Yin [15:0] $end
$var wire 16 ? Zin [15:0] $end
$var wire 1 & clk $end
$var wire 3 @ i [2:0] $end
$var wire 16 A prev_angle [15:0] $end
$var reg 16 B Xout [15:0] $end
$var reg 16 C Yout [15:0] $end
$var reg 16 D Zout [15:0] $end
$upscope $end
$scope module c2 $end
$var wire 16 E Xin [15:0] $end
$var wire 16 F Yin [15:0] $end
$var wire 16 G Zin [15:0] $end
$var wire 1 & clk $end
$var wire 3 H i [2:0] $end
$var wire 16 I prev_angle [15:0] $end
$var reg 16 J Xout [15:0] $end
$var reg 16 K Yout [15:0] $end
$var reg 16 L Zout [15:0] $end
$upscope $end
$scope module c3 $end
$var wire 16 M Xin [15:0] $end
$var wire 16 N Yin [15:0] $end
$var wire 16 O Zin [15:0] $end
$var wire 1 & clk $end
$var wire 3 P i [2:0] $end
$var wire 16 Q prev_angle [15:0] $end
$var reg 16 R Xout [15:0] $end
$var reg 16 S Yout [15:0] $end
$var reg 16 T Zout [15:0] $end
$upscope $end
$scope module c4 $end
$var wire 16 U Xin [15:0] $end
$var wire 16 V Yin [15:0] $end
$var wire 16 W Zin [15:0] $end
$var wire 1 & clk $end
$var wire 3 X i [2:0] $end
$var wire 16 Y prev_angle [15:0] $end
$var reg 16 Z Xout [15:0] $end
$var reg 16 [ Yout [15:0] $end
$var reg 16 \ Zout [15:0] $end
$upscope $end
$scope module c5 $end
$var wire 16 ] Xin [15:0] $end
$var wire 16 ^ Yin [15:0] $end
$var wire 16 _ Zin [15:0] $end
$var wire 1 & clk $end
$var wire 3 ` i [2:0] $end
$var wire 16 a prev_angle [15:0] $end
$var reg 16 b Xout [15:0] $end
$var reg 16 c Yout [15:0] $end
$var reg 16 d Zout [15:0] $end
$upscope $end
$scope module c6 $end
$var wire 16 e Xin [15:0] $end
$var wire 16 f Yin [15:0] $end
$var wire 16 g Zin [15:0] $end
$var wire 1 & clk $end
$var wire 3 h i [2:0] $end
$var wire 16 i prev_angle [15:0] $end
$var reg 16 j Xout [15:0] $end
$var reg 16 k Yout [15:0] $end
$var reg 16 l Zout [15:0] $end
$upscope $end
$scope module c7 $end
$var wire 16 m Xin [15:0] $end
$var wire 16 n Yin [15:0] $end
$var wire 16 o Zin [15:0] $end
$var wire 1 & clk $end
$var wire 3 p i [2:0] $end
$var wire 16 q prev_angle [15:0] $end
$var reg 16 r Xout [15:0] $end
$var reg 16 s Yout [15:0] $end
$var reg 16 t Zout [15:0] $end
$upscope $end
$upscope $end
$upscope $end
$enddefinitions $end
#0
$dumpvars
bx t
bx s
bx r
b1010001 q
b111 p
bx o
bx n
bx m
bx l
bx k
bx j
b10100010 i
b110 h
bx g
bx f
bx e
bx d
bx c
bx b
b101000101 a
b101 `
bx _
bx ^
bx ]
bx \
bx [
bx Z
b1010001011 Y
b100 X
bx W
bx V
bx U
bx T
bx S
bx R
b10100010001 Q
b11 P
bx O
bx N
bx M
bx L
bx K
bx J
b100111111011 I
b10 H
bx G
bx F
bx E
bx D
bx C
bx B
b1001011100100 A
b1 @
b0 ?
b0 >
b11111010000 =
b0 <
b0 ;
b11111010000 :
b10000000000000 9
b0 8
b10000000000000 7
b1111110000011000 6
b1111101000 5
r0.612 4
b10000000000000 3
b1111110000011000 2
b1111101000 1
b0 0
b0 /
bx .
bx -
bx ,
b1110000000000000 +
b1111101000 *
b1111101000 )
r315 (
b10000000000000000 '
1&
b1110000000000000 %
b1111101000 $
b1111101000 #
b0 "
b0 !
$end
#1
0&
#2
b1110110100011100 D
b1110110100011100 G
b1111101000 C
b1111101000 F
b11111010000 B
b11111010000 E
1&
#3
0&
#4
b1111011100010111 L
b1111011100010111 O
b111110100 K
b111110100 N
b100011001010 J
b100011001010 M
1&
#5
0&
#6
b1111110000101000 T
b1111110000101000 W
b11011011 S
b11011011 V
b100100001000 R
b100100001000 U
1&
#7
0&
#8
b1111111010110011 \
b1111111010110011 _
b1001011 [
b1001011 ^
b100100010101 Z
b100100010101 ]
1&
#9
0&
#10
b1111111111111000 d
b1111111111111000 g
b11 c
b11 f
b100100010111 b
b100100010111 e
1&
#11
0&
#12
b10011010 l
b10011010 o
b1111111111011111 k
b1111111111011111 n
b100100010111 j
b100100010111 m
1&
#13
0&
#14
b1001001 ,
b1001001 t
b1111111111110001 -
b1111111111110001 s
b100100011000 .
b100100011000 r
1&
#15
0&
#16
b1110000000000000 <
b1110000000000000 ?
b1111100000110000 ;
b1111100000110000 >
b0 :
b0 =
b1111111111110111 !
b1111111111110111 0
b10110010001 "
b10110010001 /
b0 7
b0 3
b1111110000011000 5
b1111110000011000 1
1&
r180 (
b1000000000000000 %
b1000000000000000 +
#17
0&
#18
b1111001011100100 D
b1111001011100100 G
b1111100000110000 C
b1111100000110000 F
b1111110000011000 B
b1111110000011000 E
1&
#19
0&
#20
b1111110011011111 L
b1111110011011111 O
b1111100100101010 K
b1111100100101010 N
b1111101000100100 J
b1111101000100100 M
1&
#21
0&
#22
b111110000 T
b111110000 W
b1111100111100110 S
b1111100111100110 V
b1111100101001001 R
b1111100101001001 U
1&
#23
0&
#24
b1111111101100101 \
b1111111101100101 _
b1111100101111010 [
b1111100101111010 ^
b1111100110101011 Z
b1111100110101011 ]
1&
#25
0&
#26
b10101010 d
b10101010 g
b1111100110101101 c
b1111100110101101 f
b1111100101110110 b
b1111100101110110 e
1&
#27
0&
#28
b1000 l
b1000 o
b1111100110010010 k
b1111100110010010 n
b1111100110010000 j
b1111100110010000 m
1&
#29
0&
#30
b1111111110110111 ,
b1111111110110111 t
b1111100110000101 -
b1111100110000101 s
b1111100110011101 .
b1111100110011101 r
1&
#31
0&
#32
b1110000100000000 <
b1110000100000000 ?
b1111101000 ;
b1111101000 >
b1111110000011000 :
b1111110000011000 =
b1111110000001001 !
b1111110000001001 0
b1111110000010111 "
b1111110000010111 /
b100000000 7
b100000000 3
b1111101000 6
b1111101000 2
b0 5
b0 1
1&
r1.40625 (
b100000000 %
b100000000 +
b0 #
b0 )
#33
0&
#34
b1111001111100100 D
b1111001111100100 G
b10111011100 C
b10111011100 F
b1111111000001100 B
b1111111000001100 E
1&
#35
0&
#36
b1111110111011111 L
b1111110111011111 O
b11001011001 K
b11001011001 N
b1111111110000011 J
b1111111110000011 M
1&
#37
0&
#38
b1011110000 T
b1011110000 W
b11001101001 S
b11001101001 V
b1001110 R
b1001110 U
1&
#39
0&
#40
b1100101 \
b1100101 _
b11001101101 [
b11001101101 ^
b1111111111101000 Z
b1111111111101000 ]
1&
#41
0&
#42
b1111111100100000 d
b1111111100100000 g
b11001101100 c
b11001101100 f
b1111111110110101 b
b1111111110110101 e
1&
#43
0&
#44
b1111111111000010 l
b1111111111000010 o
b11001101110 k
b11001101110 n
b1111111111001110 j
b1111111111001110 m
1&
#45
0&
#46
b10011 ,
b10011 t
b11001101111 -
b11001101111 s
b1111111111011010 .
b1111111111011010 r
1&
#47
0&
#48
b1000 <
b1000 ?
b1111101000 :
b1111101000 =
b1111110000 !
b1111110000 0
b1111111111101001 "
b1111111111101001 /
b10000000001000 7
b10000000001000 3
b0 6
b0 2
b1111101000 5
b1111101000 1
1&
r45.0439453125 (
b10000000001000 %
b10000000001000 +
b0 $
b0 *
b1111101000 #
b1111101000 )
#49
0&
#50
b1110110100100100 D
b1110110100100100 G
b111110100 B
b111110100 E
1&
#51
0&
#52
b1111011100011111 L
b1111011100011111 O
b10101011111 K
b10101011111 N
b1101101011 J
b1101101011 M
1&
#53
0&
#54
b1111110000110000 T
b1111110000110000 W
b10011110010 S
b10011110010 V
b10000010110 R
b10000010110 U
1&
#55
0&
#56
b1111111010111011 \
b1111111010111011 _
b10010110001 [
b10010110001 ^
b10001100101 Z
b10001100101 ]
1&
#57
0&
#58
b0 d
b0 g
b10010001110 c
b10010001110 f
b10010001010 b
b10010001010 e
1&
#59
0&
#60
b1111111101011110 l
b1111111101011110 o
b10010100000 k
b10010100000 n
b10001111000 j
b10001111000 m
1&
#61
0&
#62
b1111111110101111 ,
b1111111110101111 t
b10010011000 -
b10010011000 s
b10010000001 .
b10010000001 r
1&
#63
0&
#64
b1110000000000000 <
b1110000000000000 ?
b1111110000011000 :
b1111110000011000 =
b1011010000 !
b1011010000 0
b1011000010 "
b1011000010 /
b0 7
b0 3
b1111101000 6
b1111101000 2
b0 5
b0 1
1&
r90 (
b100000000000000 %
b100000000000000 +
#65
0&
#66
b1111001011100100 D
b1111001011100100 G
b1111111000001100 B
b1111111000001100 E
1&
#67
0&
#68
b1111110011011111 L
b1111110011011111 O
b11001011001 K
b11001011001 N
b1111111110000011 J
b1111111110000011 M
1&
#69
0&
#70
b111110000 T
b111110000 W
b11001101001 S
b11001101001 V
b1001110 R
b1001110 U
1&
#71
0&
#72
b1111111101100101 \
b1111111101100101 _
b11001101101 [
b11001101101 ^
b1111111111101000 Z
b1111111111101000 ]
1&
#73
0&
#74
b10101010 d
b10101010 g
b11001101110 c
b11001101110 f
b11011 b
b11011 e
1&
#75
0&
#76
b1000 l
b1000 o
b11001101110 k
b11001101110 n
b10 j
b10 m
1&
#77
0&
#78
b1111111110110111 ,
b1111111110110111 t
b11001101110 -
b11001101110 s
b1111111111110110 .
b1111111111110110 r
1&
#79
0&
#80
b1110001000100010 <
b1110001000100010 ?
b1111101000 :
b1111101000 =
b1111101111 !
b1111101111 0
b1111111111111010 "
b1111111111111010 /
b1000100010 7
b1000100010 3
b0 6
b0 2
b1111101000 5
b1111101000 1
1&
r2.999267578125 (
b1000100010 %
b1000100010 +
#81
0&
#82
b1111010100000110 D
b1111010100000110 G
b111110100 C
b111110100 F
b10111011100 B
b10111011100 E
1&
#83
0&
#84
b1111111100000001 L
b1111111100000001 O
b1111101 K
b1111101 N
b11001011001 J
b11001011001 M
1&
#85
0&
#86
b10000010010 T
b10000010010 W
b1111111110110010 S
b1111111110110010 V
b11001101000 R
b11001101000 U
1&
#87
0&
#88
b110000111 \
b110000111 _
b11000 [
b11000 ^
b11001101101 Z
b11001101101 ]
1&
#89
0&
#90
b1000010 d
b1000010 g
b1001011 c
b1001011 f
b11001101101 b
b11001101101 e
1&
#91
0&
#92
b1111111110100000 l
b1111111110100000 o
b1100100 k
b1100100 n
b11001101100 j
b11001101100 m
1&
#93
0&
#94
b1111111111110001 ,
b1111111111110001 t
b1011000 -
b1011000 s
b11001101100 .
b11001101100 r
1&
#95
0&
#96
b1111001000100010 <
b1111001000100010 ?
b110110 !
b110110 0
b1111101110 "
b1111101110 /
b1001000100010 7
b1001000100010 3
1&
r25.499267578125 (
b1001000100010 %
b1001000100010 +
#97
0&
#98
b10100000110 D
b10100000110 G
1&
#99
0&
#100
b1111101100001011 L
b1111101100001011 O
b1101101011 K
b1101101011 N
b10101011111 J
b10101011111 M
1&
#101
0&
#102
b11100 T
b11100 W
b1011000000 S
b1011000000 V
b10111001100 R
b10111001100 U
1&
#103
0&
#104
b1111110110010001 \
b1111110110010001 _
b1100011100 [
b1100011100 ^
b10110100000 Z
b10110100000 ]
1&
#105
0&
#106
b1111111011010110 d
b1111111011010110 g
b1011101111 c
b1011101111 f
b10110111000 b
b10110111000 e
1&
#107
0&
#108
b1111111101111000 l
b1111111101111000 o
b1011011001 k
b1011011001 n
b10111000011 j
b10111000011 m
1&
#109
0&
#110
b1111111111001001 ,
b1111111111001001 t
b1011001110 -
b1011001110 s
b10111001000 .
b10111001000 r
1&
#111
0&
#112
b110110111 !
b110110111 0
b1110001010 "
b1110001010 /
1&
