Assignment1/Third_answer/Assignment_1_c.v
module two_multipliers_and_one_adder(input wire [3:0] X0,input wire [3:0] X1,input wire [3:0] X2,input wire [3:0] X3,input wire [3:0] X4,input wire [3:0] X5,input wire [3:0] X6,input wire [3:0] X7,input wire [3:0] X8,input wire [3:0] X9,input wire [3:0] H0,input wire [3:0] H1,input wire [3:0] H2,input wire [3:0] H3,input wire [3:0] H4,input wire [3:0] H5,input wire [3:0] H6,input wire [3:0] H7,input wire [3:0] H8,input wire [3:0] H9,input clk,output reg[15:0] Y);

reg [15:0] mul1,mul2;
reg [15:0] sum[0:4];
reg [15:0] sumsecondstage[0:1];
// state is used to remember the state and perform the corresponding mux activity
reg [3:0] state = 4'b1111;
// 4 muxes are used
reg [15:0] mux1=0, mux2=0, mux3=0, mux4=0;
// 2 multipliers and adder to store multiplied values

always @(X0 or X1 or X2 or X3 or X4 or X5 or X6 or X7 or X8 or X9 or H0 or H1 or H2 or H3 or H4 or H5 or H6 or H7 or H8 or H9)
begin
    state = 4'b1111;
    // because if we start from 0 directly then we will be computing directly an addition + two multiplications without consuming any clock cycle
end

always @(posedge clk)
begin
      
      if (state < 9) 
        begin
          state <= state + 1;
        end
      else 
        begin
          state <= 4'b0000;
        end
end

always @(state) 

begin

    if (state < 9) 
        begin
            case (state)

            4'b0000: begin mux1 = X0; mux2 = H0; mux3 = X1; mux4 = H1; end
            4'b0001: begin mux1 = X2;mux2 = H2;mux3 = X3;mux4 = H3;end
            4'b0010: begin mux1 = X4;mux2 = H4;mux3 = X5;mux4 = H5;end
            4'b0011: begin mux1 = X6;mux2 = H6;mux3 = X7;mux4 = H7;end
            4'b0100: begin mux1 = X8;mux2 = H8;mux3 = X9;mux4 = H9;end
            4'b0101: begin sumsecondstage[0]= sum[0]+sum[1];end
            4'b0110: begin sumsecondstage[1]= sum[2]+sum[3];end
            4'b0111: begin sumsecondstage[1]= sumsecondstage[1]+sum[4];end
            4'b1000: begin Y= sumsecondstage[0]+sumsecondstage[1];end

            default: begin Y=0; end

            endcase

            mul1 = mux1 * mux2;
            mul2 = mux3 * mux4;
            sum[state] = mul1 + mul2;
            // Using one adder and two multipliers at a state which refers to one clock cycle 
        end

end

endmodule

Assignment1/Third_answer/Assignment_1_c_tb.v
`timescale 1ns/1ns
module Assignment_1_c_tb;
reg [3:0]X0,X1,X2,X3,X4,X5,X6,X7,X8,X9,Y0,Y1,Y2,Y3,Y4,Y5,Y6,Y7,Y8,Y9;
reg clk;
integer i;
wire [15:0]P;
always #1 clk = ~clk;

two_multipliers_and_one_adder m1(X0,X1,X2,X3,X4,X5,X6,X7,X8,X9,Y0,Y1,Y2,Y3,Y4,Y5,Y6,Y7,Y8,Y9,clk,P);

initial begin
    clk=1;
    X0=$random;X1=$random;X2=$random;X3=$random;X4=$random;X5=$random;X6=$random;X7=$random;X8=$random;X9=$random;Y0=$random;Y1=$random;Y2=$random;Y3=$random;Y4=$random;Y5=$random;Y6=$random;Y7=$random;Y8=$random;Y9=$random;
    $monitor("Time %dns X0=%d X1=%d X2=%d X3=%d X4=%d X5=%d X6=%d X7=%d X8=%d X9=%d Y0=%d Y1=%d Y2=%d Y3=%d Y4=%d Y5=%d Y6=%d Y7=%d Y8=%d Y9=%d Output=%d",$time,X0,X1,X2,X3,X4,X5,X6,X7,X8,X9,Y0,Y1,Y2,Y3,Y4,Y5,Y6,Y7,Y8,Y9,P);
    $dumpfile("3.vcd");
    $dumpvars;
    #200 $finish;
end

initial begin
 for (i=0; i<5; i++) begin
    #18
    X0=$random;X1=$random;X2=$random;X3=$random;X4=$random;X5=$random;X6=$random;X7=$random;X8=$random;X9=$random;Y0=$random;Y1=$random;Y2=$random;Y3=$random;Y4=$random;Y5=$random;Y6=$random;Y7=$random;Y8=$random;Y9=$random;
 end
end
endmodule

Assignment1/Third_answer/3.vcd
$date
	Sat Nov 26 23:40:49 2022
$end
$version
	Icarus Verilog
$end
$timescale
	1ns
$end
$scope module Assignment_1_c_tb $end
$var wire 16 ! P [15:0] $end
$var reg 4 " X0 [3:0] $end
$var reg 4 # X1 [3:0] $end
$var reg 4 $ X2 [3:0] $end
$var reg 4 % X3 [3:0] $end
$var reg 4 & X4 [3:0] $end
$var reg 4 ' X5 [3:0] $end
$var reg 4 ( X6 [3:0] $end
$var reg 4 ) X7 [3:0] $end
$var reg 4 * X8 [3:0] $end
$var reg 4 + X9 [3:0] $end
$var reg 4 , Y0 [3:0] $end
$var reg 4 - Y1 [3:0] $end
$var reg 4 . Y2 [3:0] $end
$var reg 4 / Y3 [3:0] $end
$var reg 4 0 Y4 [3:0] $end
$var reg 4 1 Y5 [3:0] $end
$var reg 4 2 Y6 [3:0] $end
$var reg 4 3 Y7 [3:0] $end
$var reg 4 4 Y8 [3:0] $end
$var reg 4 5 Y9 [3:0] $end
$var reg 1 6 clk $end
$var integer 32 7 i [31:0] $end
$scope module m1 $end
$var wire 4 8 H0 [3:0] $end
$var wire 4 9 H1 [3:0] $end
$var wire 4 : H2 [3:0] $end
$var wire 4 ; H3 [3:0] $end
$var wire 4 < H4 [3:0] $end
$var wire 4 = H5 [3:0] $end
$var wire 4 > H6 [3:0] $end
$var wire 4 ? H7 [3:0] $end
$var wire 4 @ H8 [3:0] $end
$var wire 4 A H9 [3:0] $end
$var wire 4 B X0 [3:0] $end
$var wire 4 C X1 [3:0] $end
$var wire 4 D X2 [3:0] $end
$var wire 4 E X3 [3:0] $end
$var wire 4 F X4 [3:0] $end
$var wire 4 G X5 [3:0] $end
$var wire 4 H X6 [3:0] $end
$var wire 4 I X7 [3:0] $end
$var wire 4 J X8 [3:0] $end
$var wire 4 K X9 [3:0] $end
$var wire 1 6 clk $end
$var reg 16 L Y [15:0] $end
$var reg 16 M mul1 [15:0] $end
$var reg 16 N mul2 [15:0] $end
$var reg 16 O mux1 [15:0] $end
$var reg 16 P mux2 [15:0] $end
$var reg 16 Q mux3 [15:0] $end
$var reg 16 R mux4 [15:0] $end
$var reg 4 S state [3:0] $end
$upscope $end
$upscope $end
$enddefinitions $end
#0
$dumpvars
b0 S
b1101 R
b1 Q
b110 P
b100 O
b1101 N
b11000 M
bx L
b1101 K
b1 J
b10 I
b101 H
b1101 G
b1101 F
b11 E
b1001 D
b1 C
b100 B
b111 A
b101 @
b1010 ?
b101 >
b110 =
b1001 <
b1100 ;
b1101 :
b1101 9
b110 8
b0 7
16
b111 5
b101 4
b1010 3
b101 2
b110 1
b1001 0
b1100 /
b1101 .
b1101 -
b110 ,
b1101 +
b1 *
b10 )
b101 (
b1101 '
b1101 &
b11 %
b1001 $
b1 #
b100 "
bx !
$end
#1
06
#2
b100100 N
b1110101 M
b1100 R
b11 Q
b1101 P
b1001 O
b1 S
16
#3
06
#4
b1001110 N
b110 R
b1101 Q
b1001 P
b1101 O
b10 S
16
#5
06
#6
b10100 N
b11001 M
b1010 R
b10 Q
b101 P
b101 O
b11 S
16
#7
06
#8
b1011011 N
b101 M
b111 R
b1101 Q
b1 O
b100 S
16
#9
06
#10
b101 S
16
#11
06
#12
b110 S
16
#13
06
#14
b111 S
16
#15
06
#16
b1000001110 !
b1000001110 L
b1000 S
16
#17
06
#18
b10010110 N
b110 M
b1010 R
b1111 Q
b11 P
b10 O
b0 S
16
b1 7
b11 5
b11 A
b1101 4
b1101 @
b11 3
b11 ?
b110 2
b110 >
b1101 1
b1101 =
b1010 0
b1010 <
b0 /
b0 ;
b0 .
b0 :
b1010 -
b1010 9
b11 ,
b11 8
b101 +
b101 K
b1101 *
b1101 J
b1101 )
b1101 I
b1100 (
b1100 H
b101 '
b101 G
b1000 &
b1000 F
b1110 %
b1110 E
b10 $
b10 D
b1111 #
b1111 C
b10 "
b10 B
#19
06
#20
b0 N
b0 M
b0 R
b1110 Q
b0 P
b1 S
16
#21
06
#22
b1000001 N
b1010000 M
b1101 R
b101 Q
b1010 P
b1000 O
b10 S
16
#23
06
#24
b100111 N
b1001000 M
b11 R
b1101 Q
b110 P
b1100 O
b11 S
16
#25
06
#26
b1111 N
b10101001 M
b101 Q
b1101 P
b1101 O
b100 S
16
#27
06
#28
b101 S
16
#29
06
#30
b110 S
16
#31
06
#32
b111 S
16
#33
06
#34
b1001010100 !
b1001010100 L
b1000 S
16
#35
06
#36
b110010 N
b10110 M
b1010 R
b10 P
b1011 O
b0 S
16
b10 7
b1110 5
b1110 A
b110 4
b110 @
b110 3
b110 ?
b1011 2
b1011 >
b1001 1
b1001 =
b1000 0
b1000 <
b1000 /
b1000 ;
b1 .
b1 :
b10 ,
b10 8
b1100 +
b1100 K
b1010 *
b1010 J
b1010 )
b1010 I
b11 (
b11 H
b1111 '
b1111 G
b1101 &
b1101 F
b101 #
b101 C
b1011 "
b1011 B
#37
06
#38
b1110000 N
b10 M
b1000 R
b1110 Q
b1 P
b10 O
b1 S
16
#39
06
#40
b10000111 N
b1101000 M
b1001 R
b1111 Q
b1000 P
b1101 O
b10 S
16
#41
06
#42
b111100 N
b100001 M
b110 R
b1010 Q
b1011 P
b11 O
b11 S
16
#43
06
#44
b10101000 N
b111100 M
b1110 R
b1100 Q
b110 P
b1010 O
b100 S
16
#45
06
#46
b101 S
16
#47
06
#48
b110 S
16
#49
06
#50
b111 S
16
#51
06
#52
b1011101010 !
b1011101010 L
b1000 S
16
#53
06
#54
b1011010 N
b1100 M
b1001 R
b1010 Q
b1 P
b1100 O
b0 S
16
b11 7
b1100 5
b1100 A
b1111 4
b1111 @
b111 3
b111 ?
b1000 2
b1000 >
b1111 1
b1111 =
b1111 0
b1111 <
b1100 /
b1100 ;
b10 .
b10 :
b1001 -
b1001 9
b1 ,
b1 8
b101 +
b101 K
b1110 *
b1110 J
b1011 (
b1011 H
b101 &
b101 F
b1 %
b1 E
b1011 $
b1011 D
b1010 #
b1010 C
b1100 "
b1100 B
#55
06
#56
b1100 N
b10110 M
b1100 R
b1 Q
b10 P
b1011 O
b1 S
16
#57
06
#58
b11100001 N
b1001011 M
b1111 R
b1111 Q
b1111 P
b101 O
b10 S
16
#59
06
#60
b1000110 N
b1011000 M
b111 R
b1010 Q
b1000 P
b1011 O
b11 S
16
#61
06
#62
b111100 N
b11010010 M
b1100 R
b101 Q
b1111 P
b1110 O
b100 S
16
#63
06
#64
b101 S
16
#65
06
#66
b110 S
16
#67
06
#68
b111 S
16
#69
06
#70
b1101100000 !
b1101100000 L
b1000 S
16
#71
06
#72
b1110101 N
b1001101 M
b1101 R
b1001 Q
b111 P
b1011 O
b0 S
16
b100 7
b1000 5
b1000 A
b101 4
b101 @
b11 3
b11 ?
b1111 2
b1111 >
b1001 1
b1001 =
b1101 0
b1101 <
b1110 /
b1110 ;
b1101 -
b1101 9
b111 ,
b111 8
b1000 +
b1000 K
b10 *
b10 J
b1100 )
b1100 I
b110 (
b110 H
b1 '
b1 G
b111 &
b111 F
b0 %
b0 E
b1001 $
b1001 D
b1001 #
b1001 C
b1011 "
b1011 B
#73
06
#74
b0 N
b10010 M
b1110 R
b0 Q
b10 P
b1001 O
b1 S
16
#75
06
#76
b1001 N
b1011011 M
b1001 R
b1 Q
b1101 P
b111 O
b10 S
16
#77
06
#78
b100100 N
b1011010 M
b11 R
b1100 Q
b1111 P
b110 O
b11 S
16
#79
06
#80
b1000000 N
b1010 M
b1000 R
b1000 Q
b101 P
b10 O
b100 S
16
#81
06
#82
b101 S
16
#83
06
#84
b110 S
16
#85
06
#86
b111 S
16
#87
06
#88
b1000000000 !
b1000000000 L
b1000 S
16
#89
06
#90
b11011 N
b100001 M
b11 R
b1001 Q
b11 P
b1011 O
b0 S
16
b101 7
b1010 5
b1010 A
b110 4
b110 @
b1011 3
b1011 ?
b111 2
b111 >
b100 1
b100 =
b1111 0
b1111 <
b11 /
b11 ;
b1111 .
b1111 :
b11 -
b11 9
b11 ,
b11 8
b110 +
b110 K
b1010 *
b1010 J
b1110 (
b1110 H
b110 '
b110 G
b1000 &
b1000 F
b1010 %
b1010 E
b1111 $
b1111 D
#91
06
#92
b11110 N
b11100001 M
b1010 Q
b1111 P
b1111 O
b1 S
16
#93
06
#94
b11000 N
b1111000 M
b100 R
b110 Q
b1000 O
b10 S
16
#95
06
#96
b10000100 N
b1100010 M
b1011 R
b1100 Q
b111 P
b1110 O
b11 S
16
#97
06
#98
b111100 N
b111100 M
b1010 R
b110 Q
b110 P
b1010 O
b100 S
16
#99
06
#100
b101 S
16
#101
06
#102
b110 S
16
#103
06
#104
b111 S
16
#105
06
#106
b1100101001 !
b1100101001 L
b1000 S
16
#107
06
#108
b1001 S
16
#109
06
#110
b11011 N
b100001 M
b11 R
b1001 Q
b11 P
b1011 O
b0 S
16
#111
06
#112
b11110 N
b11100001 M
b1010 Q
b1111 P
b1111 O
b1 S
16
#113
06
#114
b11000 N
b1111000 M
b100 R
b110 Q
b1000 O
b10 S
16
#115
06
#116
b10000100 N
b1100010 M
b1011 R
b1100 Q
b111 P
b1110 O
b11 S
16
#117
06
#118
b111100 N
b111100 M
b1010 R
b110 Q
b110 P
b1010 O
b100 S
16
#119
06
#120
b101 S
16
#121
06
#122
b110 S
16
#123
06
#124
b111 S
16
#125
06
#126
b1000 S
16
#127
06
#128
b1001 S
16
#129
06
#130
b11011 N
b100001 M
b11 R
b1001 Q
b11 P
b1011 O
b0 S
16
#131
06
#132
b11110 N
b11100001 M
b1010 Q
b1111 P
b1111 O
b1 S
16
#133
06
#134
b11000 N
b1111000 M
b100 R
b110 Q
b1000 O
b10 S
16
#135
06
#136
b10000100 N
b1100010 M
b1011 R
b1100 Q
b111 P
b1110 O
b11 S
16
#137
06
#138
b111100 N
b111100 M
b1010 R
b110 Q
b110 P
b1010 O
b100 S
16
#139
06
#140
b101 S
16
#141
06
#142
b110 S
16
#143
06
#144
b111 S
16
#145
06
#146
b1000 S
16
#147
06
#148
b1001 S
16
#149
06
#150
b11011 N
b100001 M
b11 R
b1001 Q
b11 P
b1011 O
b0 S
16
#151
06
#152
b11110 N
b11100001 M
b1010 Q
b1111 P
b1111 O
b1 S
16
#153
06
#154
b11000 N
b1111000 M
b100 R
b110 Q
b1000 O
b10 S
16
#155
06
#156
b10000100 N
b1100010 M
b1011 R
b1100 Q
b111 P
b1110 O
b11 S
16
#157
06
#158
b111100 N
b111100 M
b1010 R
b110 Q
b110 P
b1010 O
b100 S
16
#159
06
#160
b101 S
16
#161
06
#162
b110 S
16
#163
06
#164
b111 S
16
#165
06
#166
b1000 S
16
#167
06
#168
b1001 S
16
#169
06
#170
b11011 N
b100001 M
b11 R
b1001 Q
b11 P
b1011 O
b0 S
16
#171
06
#172
b11110 N
b11100001 M
b1010 Q
b1111 P
b1111 O
b1 S
16
#173
06
#174
b11000 N
b1111000 M
b100 R
b110 Q
b1000 O
b10 S
16
#175
06
#176
b10000100 N
b1100010 M
b1011 R
b1100 Q
b111 P
b1110 O
b11 S
16
#177
06
#178
b111100 N
b111100 M
b1010 R
b110 Q
b110 P
b1010 O
b100 S
16
#179
06
#180
b101 S
16
#181
06
#182
b110 S
16
#183
06
#184
b111 S
16
#185
06
#186
b1000 S
16
#187
06
#188
b1001 S
16
#189
06
#190
b11011 N
b100001 M
b11 R
b1001 Q
b11 P
b1011 O
b0 S
16
#191
06
#192
b11110 N
b11100001 M
b1010 Q
b1111 P
b1111 O
b1 S
16
#193
06
#194
b11000 N
b1111000 M
b100 R
b110 Q
b1000 O
b10 S
16
#195
06
#196
b10000100 N
b1100010 M
b1011 R
b1100 Q
b111 P
b1110 O
b11 S
16
#197
06
#198
b111100 N
b111100 M
b1010 R
b110 Q
b110 P
b1010 O
b100 S
16
#199
06
#200
b101 S
16
